dorc_client/__init__.py
dorc_client/auth.py
dorc_client/client.py
dorc_client/config.py
dorc_client/errors.py
dorc_client/models.py
dorc_client/version.py
dorc_client-0.2.0.dist-info/METADATA
dorc_client-0.2.0.dist-info/WHEEL
dorc_client-0.2.0.dist-info/RECORD
