Metadata-Version: 2.4
Name: dorc-client
Version: 0.2.0
Summary: Python SDK for dorc-engine HTTP API
Project-URL: Repository, https://github.com/dorc-io/dorc-clients
Project-URL: Issues, https://github.com/dorc-io/dorc-clients/issues
Author: DORC
License: Apache-2.0
Classifier: Development Status :: 3 - Alpha
Classifier: Intended Audience :: Developers
Classifier: License :: OSI Approved :: Apache Software License
Classifier: Programming Language :: Python :: 3
Classifier: Programming Language :: Python :: 3 :: Only
Classifier: Programming Language :: Python :: 3.9
Classifier: Programming Language :: Python :: 3.10
Classifier: Programming Language :: Python :: 3.11
Classifier: Programming Language :: Python :: 3.12
Classifier: Typing :: Typed
Requires-Python: >=3.9
Requires-Dist: httpx>=0.25.0
Requires-Dist: pydantic>=2.6.0
Requires-Dist: pyjwt>=2.8.0
Requires-Dist: tenacity>=8.2.0
Provides-Extra: dev
Requires-Dist: build>=1.2.0; extra == 'dev'
Requires-Dist: pytest-httpx>=0.27.0; extra == 'dev'
Requires-Dist: pytest>=7.4.0; extra == 'dev'
Requires-Dist: ruff>=0.6.0; extra == 'dev'
Requires-Dist: twine>=5.0.0; extra == 'dev'
